{
  "success": [
    {
      "id": 75094022,
      "type": "image",
      "path": "E:\\CivitAI\\Users\\Spacetoonic\\Marybell Floral Magician ( Illustrious )\\75094022.jpeg",
      "size": 125627
    },
    {
      "id": 75094013,
      "type": "image",
      "path": "E:\\CivitAI\\Users\\Spacetoonic\\Marybell Floral Magician ( Illustrious )\\75094013.jpeg",
      "size": 100921
    },
    {
      "id": 75094023,
      "type": "image",
      "path": "E:\\CivitAI\\Users\\Spacetoonic\\Marybell Floral Magician ( Illustrious )\\75094023.jpeg",
      "size": 180380
    },
    {
      "id": 75091255,
      "type": "image",
      "path": "E:\\CivitAI\\Users\\Spacetoonic\\Marybell Floral Magician ( Illustrious )\\75091255.png",
      "size": 931303
    },
    {
      "id": 1764334,
      "type": "lora",
      "path": "E:\\CivitAI\\Users\\Spacetoonic\\Marybell Floral Magician ( Illustrious )\\mariabell-000009.safetensors",
      "size": 228456364
    },
    {
      "id": 80606554,
      "type": "image",
      "path": "E:\\CivitAI\\Users\\Spacetoonic\\Gingka _ Beyblade Metal Fight ( Illustrious )\\80606554.jpeg",
      "size": 119843
    },
    {
      "id": 80606445,
      "type": "image",
      "path": "E:\\CivitAI\\Users\\Spacetoonic\\Gingka _ Beyblade Metal Fight ( Illustrious )\\80606445.jpeg",
      "size": 151811
    },
    {
      "id": 80607584,
      "type": "image",
      "path": "E:\\CivitAI\\Users\\Spacetoonic\\Gingka _ Beyblade Metal Fight ( Illustrious )\\80607584.jpeg",
      "size": 112118
    },
    {
      "id": 1870748,
      "type": "lora",
      "path": "E:\\CivitAI\\Users\\Spacetoonic\\Gingka _ Beyblade Metal Fight ( Illustrious )\\GingkaIL.safetensors",
      "size": 228453340
    },
    {
      "id": 80639105,
      "type": "image",
      "path": "E:\\CivitAI\\Users\\Spacetoonic\\Mary Lennox ( Illustrious )\\80639105.jpeg",
      "size": 125047
    },
    {
      "id": 79683205,
      "type": "image",
      "path": "E:\\CivitAI\\Users\\Spacetoonic\\Mary Lennox ( Illustrious )\\79683205.jpeg",
      "size": 157488
    },
    {
      "id": 79683207,
      "type": "image",
      "path": "E:\\CivitAI\\Users\\Spacetoonic\\Mary Lennox ( Illustrious )\\79683207.jpeg",
      "size": 162835
    },
    {
      "id": 79683204,
      "type": "image",
      "path": "E:\\CivitAI\\Users\\Spacetoonic\\Mary Lennox ( Illustrious )\\79683204.jpeg",
      "size": 140738
    },
    {
      "id": 79683201,
      "type": "image",
      "path": "E:\\CivitAI\\Users\\Spacetoonic\\Mary Lennox ( Illustrious )\\79683201.jpeg",
      "size": 120578
    },
    {
      "id": 79683206,
      "type": "image",
      "path": "E:\\CivitAI\\Users\\Spacetoonic\\Mary Lennox ( Illustrious )\\79683206.jpeg",
      "size": 135411
    },
    {
      "id": 79683202,
      "type": "image",
      "path": "E:\\CivitAI\\Users\\Spacetoonic\\Mary Lennox ( Illustrious )\\79683202.jpeg",
      "size": 124860
    },
    {
      "id": 1854497,
      "type": "lora",
      "path": "E:\\CivitAI\\Users\\Spacetoonic\\Mary Lennox ( Illustrious )\\mary_lennox.safetensors",
      "size": 228453884
    },
    {
      "id": 80677689,
      "type": "image",
      "path": "E:\\CivitAI\\Users\\Spacetoonic\\Christopher Barsac _ Secret of Cerulean sand\\80677689.jpeg",
      "size": 77256
    },
    {
      "id": 79575090,
      "type": "image",
      "path": "E:\\CivitAI\\Users\\Spacetoonic\\Christopher Barsac _ Secret of Cerulean sand\\79575090.jpeg",
      "size": 103579
    },
    {
      "id": 1850091,
      "type": "lora",
      "path": "E:\\CivitAI\\Users\\Spacetoonic\\Christopher Barsac _ Secret of Cerulean sand\\BarsacIL.safetensors",
      "size": 228453156
    },
    {
      "id": 78451491,
      "type": "image",
      "path": "E:\\CivitAI\\Users\\Spacetoonic\\dev derrian-distro IL training tesy\\78451491.jpeg",
      "size": 128597
    },
    {
      "id": 78451501,
      "type": "image",
      "path": "E:\\CivitAI\\Users\\Spacetoonic\\dev derrian-distro IL training tesy\\78451501.jpeg",
      "size": 121066
    },
    {
      "id": 1832444,
      "type": "lora",
      "path": "E:\\CivitAI\\Users\\Spacetoonic\\dev derrian-distro IL training tesy\\Mariabell2.safetensors",
      "size": 114435220
    },
    {
      "id": 81215209,
      "type": "image",
      "path": "E:\\CivitAI\\Users\\Spacetoonic\\Marrone_ Robin Hood Anime 1990 ( Illustrious ) princess version\\81215209.jpeg",
      "size": 107926
    },
    {
      "id": 81215211,
      "type": "image",
      "path": "E:\\CivitAI\\Users\\Spacetoonic\\Marrone_ Robin Hood Anime 1990 ( Illustrious ) princess version\\81215211.jpeg",
      "size": 211138
    },
    {
      "id": 81207604,
      "type": "image",
      "path": "E:\\CivitAI\\Users\\Spacetoonic\\Marrone_ Robin Hood Anime 1990 ( Illustrious ) princess version\\81207604.png",
      "size": 1363651
    },
    {
      "id": 1883041,
      "type": "lora",
      "path": "E:\\CivitAI\\Users\\Spacetoonic\\Marrone_ Robin Hood Anime 1990 ( Illustrious ) princess version\\Marion2IL.safetensors",
      "size": 228456292
    },
    {
      "id": 82665300,
      "type": "image",
      "path": "E:\\CivitAI\\Users\\Spacetoonic\\Yin _ yin yang yo ( IL\\82665300.jpeg",
      "size": 88335
    },
    {
      "id": 82665063,
      "type": "image",
      "path": "E:\\CivitAI\\Users\\Spacetoonic\\Yin _ yin yang yo ( IL\\82665063.jpeg",
      "size": 94878
    },
    {
      "id": 82665291,
      "type": "image",
      "path": "E:\\CivitAI\\Users\\Spacetoonic\\Yin _ yin yang yo ( IL\\82665291.jpeg",
      "size": 88776
    },
    {
      "id": 82665064,
      "type": "image",
      "path": "E:\\CivitAI\\Users\\Spacetoonic\\Yin _ yin yang yo ( IL\\82665064.jpeg",
      "size": 135579
    },
    {
      "id": 1908565,
      "type": "lora",
      "path": "E:\\CivitAI\\Users\\Spacetoonic\\Yin _ yin yang yo ( IL\\YinIL.safetensors",
      "size": 228456244
    },
    {
      "id": 78842895,
      "type": "image",
      "path": "E:\\CivitAI\\Users\\Spacetoonic\\Kyoya Tategami _ Beyblade Metal Fight ( Illustrious )\\78842895.jpeg",
      "size": 127406
    },
    {
      "id": 78842820,
      "type": "image",
      "path": "E:\\CivitAI\\Users\\Spacetoonic\\Kyoya Tategami _ Beyblade Metal Fight ( Illustrious )\\78842820.jpeg",
      "size": 138301
    },
    {
      "id": 78836365,
      "type": "image",
      "path": "E:\\CivitAI\\Users\\Spacetoonic\\Kyoya Tategami _ Beyblade Metal Fight ( Illustrious )\\78836365.png",
      "size": 797049
    },
    {
      "id": 78842516,
      "type": "image",
      "path": "E:\\CivitAI\\Users\\Spacetoonic\\Kyoya Tategami _ Beyblade Metal Fight ( Illustrious )\\78842516.jpeg",
      "size": 135284
    },
    {
      "id": 78836370,
      "type": "image",
      "path": "E:\\CivitAI\\Users\\Spacetoonic\\Kyoya Tategami _ Beyblade Metal Fight ( Illustrious )\\78836370.png",
      "size": 752230
    },
    {
      "id": 1836232,
      "type": "lora",
      "path": "E:\\CivitAI\\Users\\Spacetoonic\\Kyoya Tategami _ Beyblade Metal Fight ( Illustrious )\\KyoyaIL.safetensors",
      "size": 228456516
    },
    {
      "id": 31815963,
      "type": "image",
      "path": "E:\\CivitAI\\Users\\Spacetoonic\\Eriko _ Idol Densetsu Eriko\\31815963.png",
      "size": 1044556
    },
    {
      "id": 31815977,
      "type": "image",
      "path": "E:\\CivitAI\\Users\\Spacetoonic\\Eriko _ Idol Densetsu Eriko\\31815977.png",
      "size": 1055784
    },
    {
      "id": 901813,
      "type": "lora",
      "path": "E:\\CivitAI\\Users\\Spacetoonic\\Eriko _ Idol Densetsu Eriko\\eriko-000008.safetensors",
      "size": 228454916
    },
    {
      "id": 39420961,
      "type": "image",
      "path": "E:\\CivitAI\\Users\\Spacetoonic\\Nobi Nobita _ Doraemon\\39420961.jpeg",
      "size": 1079231
    },
    {
      "id": 1046777,
      "type": "lora",
      "path": "E:\\CivitAI\\Users\\Spacetoonic\\Nobi Nobita _ Doraemon\\Nobi_Nobita__Doraemon.safetensors",
      "size": 228455284
    },
    {
      "id": 25607954,
      "type": "image",
      "path": "E:\\CivitAI\\Users\\Spacetoonic\\Mie Daiwa - Battle B-Daman ( pony ) [ REQUEST ]\\25607954.jpeg",
      "size": 169082
    },
    {
      "id": 25607955,
      "type": "image",
      "path": "E:\\CivitAI\\Users\\Spacetoonic\\Mie Daiwa - Battle B-Daman ( pony ) [ REQUEST ]\\25607955.jpeg",
      "size": 159306
    },
    {
      "id": 753298,
      "type": "lora",
      "path": "E:\\CivitAI\\Users\\Spacetoonic\\Mie Daiwa - Battle B-Daman ( pony ) [ REQUEST ]\\Mie_Daiwa-000009.safetensors",
      "size": 228455580
    },
    {
      "id": 25258444,
      "type": "image",
      "path": "E:\\CivitAI\\Users\\Spacetoonic\\Robin hood ( 1990 Anime )\\25258444.jpeg",
      "size": 146575
    },
    {
      "id": 25258427,
      "type": "image",
      "path": "E:\\CivitAI\\Users\\Spacetoonic\\Robin hood ( 1990 Anime )\\25258427.jpeg",
      "size": 158090
    },
    {
      "id": 25258514,
      "type": "image",
      "path": "E:\\CivitAI\\Users\\Spacetoonic\\Robin hood ( 1990 Anime )\\25258514.jpeg",
      "size": 164617
    },
    {
      "id": 25258518,
      "type": "image",
      "path": "E:\\CivitAI\\Users\\Spacetoonic\\Robin hood ( 1990 Anime )\\25258518.jpeg",
      "size": 160810
    },
    {
      "id": 26402166,
      "type": "image",
      "path": "E:\\CivitAI\\Users\\Spacetoonic\\Robin hood ( 1990 Anime )\\26402166.jpeg",
      "size": 153343
    },
    {
      "id": 745663,
      "type": "lora",
      "path": "E:\\CivitAI\\Users\\Spacetoonic\\Robin hood ( 1990 Anime )\\Robin_hood-000008.safetensors",
      "size": 228455580
    },
    {
      "id": 80694267,
      "type": "image",
      "path": "E:\\CivitAI\\Users\\Spacetoonic\\Emily Bird Starr _ Kaze no Shoujo Emily ( Illustrious )\\80694267.jpeg",
      "size": 104254
    },
    {
      "id": 80694272,
      "type": "image",
      "path": "E:\\CivitAI\\Users\\Spacetoonic\\Emily Bird Starr _ Kaze no Shoujo Emily ( Illustrious )\\80694272.jpeg",
      "size": 128830
    },
    {
      "id": 80694270,
      "type": "image",
      "path": "E:\\CivitAI\\Users\\Spacetoonic\\Emily Bird Starr _ Kaze no Shoujo Emily ( Illustrious )\\80694270.jpeg",
      "size": 151890
    },
    {
      "id": 1872709,
      "type": "lora",
      "path": "E:\\CivitAI\\Users\\Spacetoonic\\Emily Bird Starr _ Kaze no Shoujo Emily ( Illustrious )\\EmilyIL.safetensors",
      "size": 228457188
    },
    {
      "id": 32449806,
      "type": "image",
      "path": "E:\\CivitAI\\Users\\Spacetoonic\\Kyoya Tategami _ Beyblade Metal Fight ( pony )\\32449806.jpeg",
      "size": 181581
    },
    {
      "id": 32449773,
      "type": "image",
      "path": "E:\\CivitAI\\Users\\Spacetoonic\\Kyoya Tategami _ Beyblade Metal Fight ( pony )\\32449773.jpeg",
      "size": 128297
    },
    {
      "id": 914023,
      "type": "lora",
      "path": "E:\\CivitAI\\Users\\Spacetoonic\\Kyoya Tategami _ Beyblade Metal Fight ( pony )\\Kyoya_tategami-000009.safetensors",
      "size": 228455116
    },
    {
      "id": 86044191,
      "type": "image",
      "path": "E:\\CivitAI\\Users\\Spacetoonic\\Masumunne Kadoya _ Beyblade metal masters ( IL )\\86044191.jpeg",
      "size": 148986
    },
    {
      "id": 86044230,
      "type": "image",
      "path": "E:\\CivitAI\\Users\\Spacetoonic\\Masumunne Kadoya _ Beyblade metal masters ( IL )\\86044230.jpeg",
      "size": 127688
    },
    {
      "id": 1969393,
      "type": "lora",
      "path": "E:\\CivitAI\\Users\\Spacetoonic\\Masumunne Kadoya _ Beyblade metal masters ( IL )\\masumunne.safetensors",
      "size": 228455740
    },
    {
      "id": 80641168,
      "type": "image",
      "path": "E:\\CivitAI\\Users\\Spacetoonic\\Jane Buxton _ Patapata Hikousen No Bouken ( Illustrious )\\80641168.jpeg",
      "size": 84498
    },
    {
      "id": 64970094,
      "type": "image",
      "path": "E:\\CivitAI\\Users\\Spacetoonic\\Jane Buxton _ Patapata Hikousen No Bouken ( Illustrious )\\64970094.jpeg",
      "size": 123199
    },
    {
      "id": 64970098,
      "type": "image",
      "path": "E:\\CivitAI\\Users\\Spacetoonic\\Jane Buxton _ Patapata Hikousen No Bouken ( Illustrious )\\64970098.jpeg",
      "size": 198595
    },
    {
      "id": 64970097,
      "type": "image",
      "path": "E:\\CivitAI\\Users\\Spacetoonic\\Jane Buxton _ Patapata Hikousen No Bouken ( Illustrious )\\64970097.jpeg",
      "size": 221898
    },
    {
      "id": 75178238,
      "type": "image",
      "path": "E:\\CivitAI\\Users\\Spacetoonic\\Minky momo ( Illustrious)\\75178238.png",
      "size": 886235
    },
    {
      "id": 75178245,
      "type": "image",
      "path": "E:\\CivitAI\\Users\\Spacetoonic\\Minky momo ( Illustrious)\\75178245.png",
      "size": 821532
    },
    {
      "id": 1765719,
      "type": "lora",
      "path": "E:\\CivitAI\\Users\\Spacetoonic\\Minky momo ( Illustrious)\\Minky_momo.safetensors",
      "size": 228457348
    },
    {
      "id": 93031850,
      "type": "image",
      "path": "E:\\CivitAI\\Users\\Spacetoonic\\Marcenai _ Patapata Hikousen No Bouken ( IL )\\93031850.jpeg",
      "size": 68399
    },
    {
      "id": 93031852,
      "type": "image",
      "path": "E:\\CivitAI\\Users\\Spacetoonic\\Marcenai _ Patapata Hikousen No Bouken ( IL )\\93031852.jpeg",
      "size": 89622
    },
    {
      "id": 93029240,
      "type": "image",
      "path": "E:\\CivitAI\\Users\\Spacetoonic\\Marcenai _ Patapata Hikousen No Bouken ( IL )\\93029240.png",
      "size": 772723
    },
    {
      "id": 2091631,
      "type": "lora",
      "path": "E:\\CivitAI\\Users\\Spacetoonic\\Marcenai _ Patapata Hikousen No Bouken ( IL )\\marcenai.safetensors",
      "size": 228456020
    },
    {
      "id": 82864571,
      "type": "image",
      "path": "E:\\CivitAI\\Users\\Spacetoonic\\LuckyPrescott _ Spirit series ( IL )\\82864571.png",
      "size": 1823853
    },
    {
      "id": 29537399,
      "type": "image",
      "path": "E:\\CivitAI\\Users\\Spacetoonic\\Saburi _ Secret of Cerulean sand (Pony)\\29537399.jpeg",
      "size": 130976
    },
    {
      "id": 29537392,
      "type": "image",
      "path": "E:\\CivitAI\\Users\\Spacetoonic\\Saburi _ Secret of Cerulean sand (Pony)\\29537392.jpeg",
      "size": 131400
    },
    {
      "id": 844988,
      "type": "lora",
      "path": "E:\\CivitAI\\Users\\Spacetoonic\\Saburi _ Secret of Cerulean sand (Pony)\\Saburi-000007.safetensors",
      "size": 228454692
    },
    {
      "id": 25557023,
      "type": "image",
      "path": "E:\\CivitAI\\Users\\Spacetoonic\\Will Scarlet _ Robin Hood ( 1990 anime ) [ REQUEST ]\\25557023.jpeg",
      "size": 98502
    },
    {
      "id": 25557098,
      "type": "image",
      "path": "E:\\CivitAI\\Users\\Spacetoonic\\Will Scarlet _ Robin Hood ( 1990 anime ) [ REQUEST ]\\25557098.jpeg",
      "size": 94138
    },
    {
      "id": 80639593,
      "type": "image",
      "path": "E:\\CivitAI\\Users\\Spacetoonic\\Chinmi _ Kung fu Chinmi ( Illustriuos )\\80639593.jpeg",
      "size": 70410
    },
    {
      "id": 1019490,
      "type": "lora",
      "path": "E:\\CivitAI\\Users\\Spacetoonic\\Chinmi _ Kung fu Chinmi ( Illustriuos )\\Chinmi.safetensors",
      "size": 228454996
    },
    {
      "id": 26229350,
      "type": "image",
      "path": "E:\\CivitAI\\Users\\Spacetoonic\\Leo - Baskup [ REQUEST ]\\26229350.jpeg",
      "size": 118598
    },
    {
      "id": 26229355,
      "type": "image",
      "path": "E:\\CivitAI\\Users\\Spacetoonic\\Leo - Baskup [ REQUEST ]\\26229355.jpeg",
      "size": 127176
    },
    {
      "id": 26229686,
      "type": "image",
      "path": "E:\\CivitAI\\Users\\Spacetoonic\\Leo - Baskup [ REQUEST ]\\26229686.jpeg",
      "size": 154053
    },
    {
      "id": 770273,
      "type": "lora",
      "path": "E:\\CivitAI\\Users\\Spacetoonic\\Leo - Baskup [ REQUEST ]\\Leo-000008.safetensors",
      "size": 228455412
    },
    {
      "id": 39223914,
      "type": "image",
      "path": "E:\\CivitAI\\Users\\Spacetoonic\\Romeo & Alfredo _ Romeo's blue skies\\39223914.jpeg",
      "size": 787437
    },
    {
      "id": 39223913,
      "type": "image",
      "path": "E:\\CivitAI\\Users\\Spacetoonic\\Romeo & Alfredo _ Romeo's blue skies\\39223913.jpeg",
      "size": 746933
    },
    {
      "id": 1044114,
      "type": "lora",
      "path": "E:\\CivitAI\\Users\\Spacetoonic\\Romeo & Alfredo _ Romeo's blue skies\\Romeo__Alfredo.safetensors",
      "size": 228455732
    },
    {
      "id": 57757655,
      "type": "image",
      "path": "E:\\CivitAI\\Users\\Spacetoonic\\Chinmi _ Iron fist chinmi\\57757655.jpeg",
      "size": 94409
    },
    {
      "id": 57757656,
      "type": "image",
      "path": "E:\\CivitAI\\Users\\Spacetoonic\\Chinmi _ Iron fist chinmi\\57757656.jpeg",
      "size": 117808
    },
    {
      "id": 25417498,
      "type": "image",
      "path": "E:\\CivitAI\\Users\\Spacetoonic\\Yamato Delgado _ Battle B-daman ( pony )\\25417498.jpeg",
      "size": 148178
    },
    {
      "id": 25417688,
      "type": "image",
      "path": "E:\\CivitAI\\Users\\Spacetoonic\\Yamato Delgado _ Battle B-daman ( pony )\\25417688.jpeg",
      "size": 176186
    },
    {
      "id": 89085942,
      "type": "image",
      "path": "E:\\CivitAI\\Users\\Spacetoonic\\street football cartoon _ character packs ( IL )\\89085942.png",
      "size": 667824
    },
    {
      "id": 89087161,
      "type": "image",
      "path": "E:\\CivitAI\\Users\\Spacetoonic\\street football cartoon _ character packs ( IL )\\89087161.jpeg",
      "size": 102475
    },
    {
      "id": 89087349,
      "type": "image",
      "path": "E:\\CivitAI\\Users\\Spacetoonic\\street football cartoon _ character packs ( IL )\\89087349.jpeg",
      "size": 194568
    },
    {
      "id": 89087221,
      "type": "image",
      "path": "E:\\CivitAI\\Users\\Spacetoonic\\street football cartoon _ character packs ( IL )\\89087221.jpeg",
      "size": 120912
    },
    {
      "id": 89087415,
      "type": "image",
      "path": "E:\\CivitAI\\Users\\Spacetoonic\\street football cartoon _ character packs ( IL )\\89087415.jpeg",
      "size": 127414
    },
    {
      "id": 89088253,
      "type": "image",
      "path": "E:\\CivitAI\\Users\\Spacetoonic\\street football cartoon _ character packs ( IL )\\89088253.jpeg",
      "size": 82336
    },
    {
      "id": 82188364,
      "type": "image",
      "path": "E:\\CivitAI\\Users\\Spacetoonic\\Tsubasa Otori _ Beyblade Metal Fight ( Illustrious )\\82188364.jpeg",
      "size": 92889
    }
  ],
  "failed": [
    {
      "id": 75094025,
      "type": "image",
      "reason": "missing",
      "info": {
        "expected_file_path": "E:\\CivitAI\\Users\\Spacetoonic\\Marybell Floral Magician ( Illustrious )\\75094025.jpeg",
        "expected_file_size": null,
        "download_url": "https://image.civitai.com/xG1nkqKTMzGDvpLrqFT7WA/62d15ef4-01b2-490f-86d3-2e9160b7bbd9/original=true/62d15ef4-01b2-490f-86d3-2e9160b7bbd9.jpeg",
        "page_url": "https://civitai.com/images/75094025"
      }
    },
    {
      "id": 75091275,
      "type": "image",
      "reason": "missing",
      "info": {
        "expected_file_path": "E:\\CivitAI\\Users\\Spacetoonic\\Marybell Floral Magician ( Illustrious )\\75091275.jpeg",
        "expected_file_size": null,
        "download_url": "https://image.civitai.com/xG1nkqKTMzGDvpLrqFT7WA/0f53c8e7-a57c-4da9-927d-56e8795e62c5/original=true/0f53c8e7-a57c-4da9-927d-56e8795e62c5.jpeg",
        "page_url": "https://civitai.com/images/75091275"
      }
    },
    {
      "id": 75094026,
      "type": "image",
      "reason": "missing",
      "info": {
        "expected_file_path": "E:\\CivitAI\\Users\\Spacetoonic\\Marybell Floral Magician ( Illustrious )\\75094026.jpeg",
        "expected_file_size": null,
        "download_url": "https://image.civitai.com/xG1nkqKTMzGDvpLrqFT7WA/2b15ed6e-a460-403f-a536-d10dc4b7d829/original=true/2b15ed6e-a460-403f-a536-d10dc4b7d829.jpeg",
        "page_url": "https://civitai.com/images/75094026"
      }
    },
    {
      "id": 80606369,
      "type": "image",
      "reason": "missing",
      "info": {
        "expected_file_path": "E:\\CivitAI\\Users\\Spacetoonic\\Gingka _ Beyblade Metal Fight ( Illustrious )\\80606369.jpeg",
        "expected_file_size": null,
        "download_url": "https://image.civitai.com/xG1nkqKTMzGDvpLrqFT7WA/3c5464ae-66c3-4e15-a284-c8aaa9db74ba/original=true/3c5464ae-66c3-4e15-a284-c8aaa9db74ba.jpeg",
        "page_url": "https://civitai.com/images/80606369"
      }
    },
    {
      "id": 79683208,
      "type": "image",
      "reason": "missing",
      "info": {
        "expected_file_path": "E:\\CivitAI\\Users\\Spacetoonic\\Mary Lennox ( Illustrious )\\79683208.jpeg",
        "expected_file_size": null,
        "download_url": "https://image.civitai.com/xG1nkqKTMzGDvpLrqFT7WA/1856f535-d2ea-4feb-b075-4e8baf1f3798/original=true/1856f535-d2ea-4feb-b075-4e8baf1f3798.jpeg",
        "page_url": "https://civitai.com/images/79683208"
      }
    },
    {
      "id": 79575097,
      "type": "image",
      "reason": "missing",
      "info": {
        "expected_file_path": "E:\\CivitAI\\Users\\Spacetoonic\\Christopher Barsac _ Secret of Cerulean sand\\79575097.jpeg",
        "expected_file_size": null,
        "download_url": "https://image.civitai.com/xG1nkqKTMzGDvpLrqFT7WA/54973482-14a3-47b5-81fb-0036b2e5c1ff/original=true/54973482-14a3-47b5-81fb-0036b2e5c1ff.jpeg",
        "page_url": "https://civitai.com/images/79575097"
      }
    },
    {
      "id": 79575082,
      "type": "image",
      "reason": "missing",
      "info": {
        "expected_file_path": "E:\\CivitAI\\Users\\Spacetoonic\\Christopher Barsac _ Secret of Cerulean sand\\79575082.jpeg",
        "expected_file_size": null,
        "download_url": "https://image.civitai.com/xG1nkqKTMzGDvpLrqFT7WA/7bfee2cf-aa69-49f8-8a62-243ab66c3de5/original=true/7bfee2cf-aa69-49f8-8a62-243ab66c3de5.jpeg",
        "page_url": "https://civitai.com/images/79575082"
      }
    },
    {
      "id": 78451547,
      "type": "image",
      "reason": "missing",
      "info": {
        "expected_file_path": "E:\\CivitAI\\Users\\Spacetoonic\\dev derrian-distro IL training tesy\\78451547.jpeg",
        "expected_file_size": null,
        "download_url": "https://image.civitai.com/xG1nkqKTMzGDvpLrqFT7WA/3431bf29-97a9-42e7-b9e4-d2b6e910a007/original=true/3431bf29-97a9-42e7-b9e4-d2b6e910a007.jpeg",
        "page_url": "https://civitai.com/images/78451547"
      }
    },
    {
      "id": 81215210,
      "type": "image",
      "reason": "missing",
      "info": {
        "expected_file_path": "E:\\CivitAI\\Users\\Spacetoonic\\Marrone_ Robin Hood Anime 1990 ( Illustrious ) princess version\\81215210.jpeg",
        "expected_file_size": null,
        "download_url": "https://image.civitai.com/xG1nkqKTMzGDvpLrqFT7WA/0a74ef49-d404-4735-9d05-7085eb841ff4/original=true/0a74ef49-d404-4735-9d05-7085eb841ff4.jpeg",
        "page_url": "https://civitai.com/images/81215210"
      }
    },
    {
      "id": 81215212,
      "type": "image",
      "reason": "missing",
      "info": {
        "expected_file_path": "E:\\CivitAI\\Users\\Spacetoonic\\Marrone_ Robin Hood Anime 1990 ( Illustrious ) princess version\\81215212.jpeg",
        "expected_file_size": null,
        "download_url": "https://image.civitai.com/xG1nkqKTMzGDvpLrqFT7WA/9decf1d2-3e2d-4567-bc71-3f7eb9e5b09d/original=true/9decf1d2-3e2d-4567-bc71-3f7eb9e5b09d.jpeg",
        "page_url": "https://civitai.com/images/81215212"
      }
    },
    {
      "id": 81215214,
      "type": "image",
      "reason": "missing",
      "info": {
        "expected_file_path": "E:\\CivitAI\\Users\\Spacetoonic\\Marrone_ Robin Hood Anime 1990 ( Illustrious ) princess version\\81215214.jpeg",
        "expected_file_size": null,
        "download_url": "https://image.civitai.com/xG1nkqKTMzGDvpLrqFT7WA/3b110ead-03fd-43a1-ba7c-3ed1afd996d5/original=true/3b110ead-03fd-43a1-ba7c-3ed1afd996d5.jpeg",
        "page_url": "https://civitai.com/images/81215214"
      }
    },
    {
      "id": 82665061,
      "type": "image",
      "reason": "missing",
      "info": {
        "expected_file_path": "E:\\CivitAI\\Users\\Spacetoonic\\Yin _ yin yang yo ( IL\\82665061.jpeg",
        "expected_file_size": null,
        "download_url": "https://image.civitai.com/xG1nkqKTMzGDvpLrqFT7WA/55e045cb-d497-4a9f-828d-2bb0f685dc1a/original=true/55e045cb-d497-4a9f-828d-2bb0f685dc1a.jpeg",
        "page_url": "https://civitai.com/images/82665061"
      }
    },
    {
      "id": 82665062,
      "type": "image",
      "reason": "missing",
      "info": {
        "expected_file_path": "E:\\CivitAI\\Users\\Spacetoonic\\Yin _ yin yang yo ( IL\\82665062.jpeg",
        "expected_file_size": null,
        "download_url": "https://image.civitai.com/xG1nkqKTMzGDvpLrqFT7WA/6c59b92b-de9f-475e-b90f-b9cd7f9e9ece/original=true/6c59b92b-de9f-475e-b90f-b9cd7f9e9ece.jpeg",
        "page_url": "https://civitai.com/images/82665062"
      }
    },
    {
      "id": 82665066,
      "type": "image",
      "reason": "missing",
      "info": {
        "expected_file_path": "E:\\CivitAI\\Users\\Spacetoonic\\Yin _ yin yang yo ( IL\\82665066.jpeg",
        "expected_file_size": null,
        "download_url": "https://image.civitai.com/xG1nkqKTMzGDvpLrqFT7WA/194c75bf-5c98-4084-b69a-7232e3f5891a/original=true/194c75bf-5c98-4084-b69a-7232e3f5891a.jpeg",
        "page_url": "https://civitai.com/images/82665066"
      }
    },
    {
      "id": 80638941,
      "type": "image",
      "reason": "missing",
      "info": {
        "expected_file_path": "E:\\CivitAI\\Users\\Spacetoonic\\Kyoya Tategami _ Beyblade Metal Fight ( Illustrious )\\80638941.jpeg",
        "expected_file_size": null,
        "download_url": "https://image.civitai.com/xG1nkqKTMzGDvpLrqFT7WA/0ac96e6a-ac08-46d8-8b1f-7fcb10863b22/original=true/0ac96e6a-ac08-46d8-8b1f-7fcb10863b22.jpeg",
        "page_url": "https://civitai.com/images/80638941"
      }
    },
    {
      "id": 78836366,
      "type": "image",
      "reason": "missing",
      "info": {
        "expected_file_path": "E:\\CivitAI\\Users\\Spacetoonic\\Kyoya Tategami _ Beyblade Metal Fight ( Illustrious )\\78836366.jpeg",
        "expected_file_size": null,
        "download_url": "https://image.civitai.com/xG1nkqKTMzGDvpLrqFT7WA/dc7b9d91-3b49-48bf-9b7e-19c5f58b6219/original=true/dc7b9d91-3b49-48bf-9b7e-19c5f58b6219.jpeg",
        "page_url": "https://civitai.com/images/78836366"
      }
    },
    {
      "id": 78842535,
      "type": "image",
      "reason": "missing",
      "info": {
        "expected_file_path": "E:\\CivitAI\\Users\\Spacetoonic\\Kyoya Tategami _ Beyblade Metal Fight ( Illustrious )\\78842535.jpeg",
        "expected_file_size": null,
        "download_url": "https://image.civitai.com/xG1nkqKTMzGDvpLrqFT7WA/6471e046-4fbd-4e8c-8f9e-5f70aac92f4c/original=true/6471e046-4fbd-4e8c-8f9e-5f70aac92f4c.jpeg",
        "page_url": "https://civitai.com/images/78842535"
      }
    },
    {
      "id": 78842806,
      "type": "image",
      "reason": "missing",
      "info": {
        "expected_file_path": "E:\\CivitAI\\Users\\Spacetoonic\\Kyoya Tategami _ Beyblade Metal Fight ( Illustrious )\\78842806.jpeg",
        "expected_file_size": null,
        "download_url": "https://image.civitai.com/xG1nkqKTMzGDvpLrqFT7WA/e1271629-3ddd-4fd0-8485-a91ba2cb31cb/original=true/e1271629-3ddd-4fd0-8485-a91ba2cb31cb.jpeg",
        "page_url": "https://civitai.com/images/78842806"
      }
    },
    {
      "id": 31815979,
      "type": "image",
      "reason": "missing",
      "info": {
        "expected_file_path": "E:\\CivitAI\\Users\\Spacetoonic\\Eriko _ Idol Densetsu Eriko\\31815979.jpeg",
        "expected_file_size": null,
        "download_url": "https://image.civitai.com/xG1nkqKTMzGDvpLrqFT7WA/689e9d61-920e-450c-8439-750295cff89b/original=true/689e9d61-920e-450c-8439-750295cff89b.jpeg",
        "page_url": "https://civitai.com/images/31815979"
      }
    },
    {
      "id": 39420963,
      "type": "image",
      "reason": "missing",
      "info": {
        "expected_file_path": "E:\\CivitAI\\Users\\Spacetoonic\\Nobi Nobita _ Doraemon\\39420963.jpeg",
        "expected_file_size": null,
        "download_url": "https://image.civitai.com/xG1nkqKTMzGDvpLrqFT7WA/8c9f1a71-483c-4991-8bb1-adc9c48130f8/original=true/8c9f1a71-483c-4991-8bb1-adc9c48130f8.jpeg",
        "page_url": "https://civitai.com/images/39420963"
      }
    },
    {
      "id": 25258437,
      "type": "image",
      "reason": "missing",
      "info": {
        "expected_file_path": "E:\\CivitAI\\Users\\Spacetoonic\\Robin hood ( 1990 Anime )\\25258437.jpeg",
        "expected_file_size": null,
        "download_url": "https://image.civitai.com/xG1nkqKTMzGDvpLrqFT7WA/4e88c71f-7c4f-4164-88b8-d373a347892b/original=true/4e88c71f-7c4f-4164-88b8-d373a347892b.jpeg",
        "page_url": "https://civitai.com/images/25258437"
      }
    },
    {
      "id": 25258447,
      "type": "image",
      "reason": "missing",
      "info": {
        "expected_file_path": "E:\\CivitAI\\Users\\Spacetoonic\\Robin hood ( 1990 Anime )\\25258447.jpeg",
        "expected_file_size": null,
        "download_url": "https://image.civitai.com/xG1nkqKTMzGDvpLrqFT7WA/c3be70d6-253e-4a04-ae24-46309dad5432/original=true/c3be70d6-253e-4a04-ae24-46309dad5432.jpeg",
        "page_url": "https://civitai.com/images/25258447"
      }
    },
    {
      "id": 25258499,
      "type": "image",
      "reason": "missing",
      "info": {
        "expected_file_path": "E:\\CivitAI\\Users\\Spacetoonic\\Robin hood ( 1990 Anime )\\25258499.jpeg",
        "expected_file_size": null,
        "download_url": "https://image.civitai.com/xG1nkqKTMzGDvpLrqFT7WA/73a24953-0767-41b3-97a5-773e284ac834/original=true/73a24953-0767-41b3-97a5-773e284ac834.jpeg",
        "page_url": "https://civitai.com/images/25258499"
      }
    },
    {
      "id": 25258468,
      "type": "image",
      "reason": "missing",
      "info": {
        "expected_file_path": "E:\\CivitAI\\Users\\Spacetoonic\\Robin hood ( 1990 Anime )\\25258468.jpeg",
        "expected_file_size": null,
        "download_url": "https://image.civitai.com/xG1nkqKTMzGDvpLrqFT7WA/cc7d165e-37a6-4ee9-aff2-1c7023ad6567/original=true/cc7d165e-37a6-4ee9-aff2-1c7023ad6567.jpeg",
        "page_url": "https://civitai.com/images/25258468"
      }
    },
    {
      "id": 80694269,
      "type": "image",
      "reason": "missing",
      "info": {
        "expected_file_path": "E:\\CivitAI\\Users\\Spacetoonic\\Emily Bird Starr _ Kaze no Shoujo Emily ( Illustrious )\\80694269.jpeg",
        "expected_file_size": null,
        "download_url": "https://image.civitai.com/xG1nkqKTMzGDvpLrqFT7WA/55619fa2-5fae-472f-8a34-4a7c2daa8ac9/original=true/55619fa2-5fae-472f-8a34-4a7c2daa8ac9.jpeg",
        "page_url": "https://civitai.com/images/80694269"
      }
    },
    {
      "id": 80694268,
      "type": "image",
      "reason": "missing",
      "info": {
        "expected_file_path": "E:\\CivitAI\\Users\\Spacetoonic\\Emily Bird Starr _ Kaze no Shoujo Emily ( Illustrious )\\80694268.jpeg",
        "expected_file_size": null,
        "download_url": "https://image.civitai.com/xG1nkqKTMzGDvpLrqFT7WA/d65f8feb-cb76-4b5e-94cb-a9122300a883/original=true/d65f8feb-cb76-4b5e-94cb-a9122300a883.jpeg",
        "page_url": "https://civitai.com/images/80694268"
      }
    },
    {
      "id": 32449778,
      "type": "image",
      "reason": "missing",
      "info": {
        "expected_file_path": "E:\\CivitAI\\Users\\Spacetoonic\\Kyoya Tategami _ Beyblade Metal Fight ( pony )\\32449778.jpeg",
        "expected_file_size": null,
        "download_url": "https://image.civitai.com/xG1nkqKTMzGDvpLrqFT7WA/0d00aed7-b4df-4322-b429-e96d83040c76/original=true/0d00aed7-b4df-4322-b429-e96d83040c76.jpeg",
        "page_url": "https://civitai.com/images/32449778"
      }
    },
    {
      "id": 86044964,
      "type": "image",
      "reason": "missing",
      "info": {
        "expected_file_path": "E:\\CivitAI\\Users\\Spacetoonic\\Masumunne Kadoya _ Beyblade metal masters ( IL )\\86044964.jpeg",
        "expected_file_size": null,
        "download_url": "https://image.civitai.com/xG1nkqKTMzGDvpLrqFT7WA/73127b78-66be-4dd5-ab12-de508236aeec/original=true/73127b78-66be-4dd5-ab12-de508236aeec.jpeg",
        "page_url": "https://civitai.com/images/86044964"
      }
    },
    {
      "id": 86044207,
      "type": "image",
      "reason": "missing",
      "info": {
        "expected_file_path": "E:\\CivitAI\\Users\\Spacetoonic\\Masumunne Kadoya _ Beyblade metal masters ( IL )\\86044207.jpeg",
        "expected_file_size": null,
        "download_url": "https://image.civitai.com/xG1nkqKTMzGDvpLrqFT7WA/0ac9c10b-c76c-4695-b7da-2faacef2f4be/original=true/0ac9c10b-c76c-4695-b7da-2faacef2f4be.jpeg",
        "page_url": "https://civitai.com/images/86044207"
      }
    },
    {
      "id": 80638889,
      "type": "image",
      "reason": "missing",
      "info": {
        "expected_file_path": "E:\\CivitAI\\Users\\Spacetoonic\\Jane Buxton _ Patapata Hikousen No Bouken ( Illustrious )\\80638889.jpeg",
        "expected_file_size": null,
        "download_url": "https://image.civitai.com/xG1nkqKTMzGDvpLrqFT7WA/518c9ee9-9304-4bef-a5a1-12036a7ff057/original=true/518c9ee9-9304-4bef-a5a1-12036a7ff057.jpeg",
        "page_url": "https://civitai.com/images/80638889"
      }
    },
    {
      "id": 64970099,
      "type": "image",
      "reason": "missing",
      "info": {
        "expected_file_path": "E:\\CivitAI\\Users\\Spacetoonic\\Jane Buxton _ Patapata Hikousen No Bouken ( Illustrious )\\64970099.jpeg",
        "expected_file_size": null,
        "download_url": "https://image.civitai.com/xG1nkqKTMzGDvpLrqFT7WA/8309cdaf-1a95-49b7-887d-d5c7a67946d2/original=true/8309cdaf-1a95-49b7-887d-d5c7a67946d2.jpeg",
        "page_url": "https://civitai.com/images/64970099"
      }
    },
    {
      "id": 64970095,
      "type": "image",
      "reason": "missing",
      "info": {
        "expected_file_path": "E:\\CivitAI\\Users\\Spacetoonic\\Jane Buxton _ Patapata Hikousen No Bouken ( Illustrious )\\64970095.jpeg",
        "expected_file_size": null,
        "download_url": "https://image.civitai.com/xG1nkqKTMzGDvpLrqFT7WA/32d86f8e-cd14-4971-a7bd-24fc7452dd80/original=true/32d86f8e-cd14-4971-a7bd-24fc7452dd80.jpeg",
        "page_url": "https://civitai.com/images/64970095"
      }
    },
    {
      "id": 64970100,
      "type": "image",
      "reason": "missing",
      "info": {
        "expected_file_path": "E:\\CivitAI\\Users\\Spacetoonic\\Jane Buxton _ Patapata Hikousen No Bouken ( Illustrious )\\64970100.jpeg",
        "expected_file_size": null,
        "download_url": "https://image.civitai.com/xG1nkqKTMzGDvpLrqFT7WA/d9903ace-3012-4f2a-b571-e5ab8fc82300/original=true/d9903ace-3012-4f2a-b571-e5ab8fc82300.jpeg",
        "page_url": "https://civitai.com/images/64970100"
      }
    },
    {
      "id": 64970052,
      "type": "image",
      "reason": "missing",
      "info": {
        "expected_file_path": "E:\\CivitAI\\Users\\Spacetoonic\\Jane Buxton _ Patapata Hikousen No Bouken ( Illustrious )\\64970052.jpeg",
        "expected_file_size": null,
        "download_url": "https://image.civitai.com/xG1nkqKTMzGDvpLrqFT7WA/2c062b99-0ef5-4b80-b5a7-d1846ab8fce4/original=true/2c062b99-0ef5-4b80-b5a7-d1846ab8fce4.jpeg",
        "page_url": "https://civitai.com/images/64970052"
      }
    },
    {
      "id": 1562582,
      "type": "lora",
      "reason": "missing",
      "info": {
        "expected_file_path": "E:\\CivitAI\\Users\\Spacetoonic\\Jane Buxton _ Patapata Hikousen No Bouken ( Illustrious )\\Jane_Buxton.safetensors",
        "expected_file_size": 228456132.0,
        "presigned_url": "https://civitai-delivery-worker-prod.5ac0637cfd0766c97916cefa3764fbdf.r2.cloudflarestorage.com/modelVersion/1562582/Jane_Buxton.safetensors?X-Amz-Expires=86400&response-content-disposition=attachment%3B%20filename%3D%22Jane_Buxton.safetensors%22&X-Amz-Algorithm=AWS4-HMAC-SHA256&X-Amz-Credential=e01358d793ad6966166af8b3064953ad/20251211/us-east-1/s3/aws4_request&X-Amz-Date=20251211T040128Z&X-Amz-SignedHeaders=host&X-Amz-Signature=455a12265aa276f7ff990c946a81c0481706c517333cbd5234513d6953dab0a7"
      }
    },
    {
      "id": 80640514,
      "type": "image",
      "reason": "missing",
      "info": {
        "expected_file_path": "E:\\CivitAI\\Users\\Spacetoonic\\Minky momo ( Illustrious)\\80640514.jpeg",
        "expected_file_size": null,
        "download_url": "https://image.civitai.com/xG1nkqKTMzGDvpLrqFT7WA/12c81fa9-c62e-4f9a-bcdf-f1cafe7b21de/original=true/12c81fa9-c62e-4f9a-bcdf-f1cafe7b21de.jpeg",
        "page_url": "https://civitai.com/images/80640514"
      }
    },
    {
      "id": 75178252,
      "type": "image",
      "reason": "missing",
      "info": {
        "expected_file_path": "E:\\CivitAI\\Users\\Spacetoonic\\Minky momo ( Illustrious)\\75178252.jpeg",
        "expected_file_size": null,
        "download_url": "https://image.civitai.com/xG1nkqKTMzGDvpLrqFT7WA/fed0f57a-ffc1-41ad-89d6-6997bf7925ab/original=true/fed0f57a-ffc1-41ad-89d6-6997bf7925ab.jpeg",
        "page_url": "https://civitai.com/images/75178252"
      }
    },
    {
      "id": 93031903,
      "type": "image",
      "reason": "missing",
      "info": {
        "expected_file_path": "E:\\CivitAI\\Users\\Spacetoonic\\Marcenai _ Patapata Hikousen No Bouken ( IL )\\93031903.jpeg",
        "expected_file_size": null,
        "download_url": "https://image.civitai.com/xG1nkqKTMzGDvpLrqFT7WA/ac6813fb-2c0c-4bee-b9ea-a22c36e28cc2/original=true/ac6813fb-2c0c-4bee-b9ea-a22c36e28cc2.jpeg",
        "page_url": "https://civitai.com/images/93031903"
      }
    },
    {
      "id": 93031878,
      "type": "image",
      "reason": "missing",
      "info": {
        "expected_file_path": "E:\\CivitAI\\Users\\Spacetoonic\\Marcenai _ Patapata Hikousen No Bouken ( IL )\\93031878.jpeg",
        "expected_file_size": null,
        "download_url": "https://image.civitai.com/xG1nkqKTMzGDvpLrqFT7WA/950ddcc1-6e45-4588-ba10-1ad5e6975179/original=true/950ddcc1-6e45-4588-ba10-1ad5e6975179.jpeg",
        "page_url": "https://civitai.com/images/93031878"
      }
    },
    {
      "id": 82864573,
      "type": "image",
      "reason": "missing",
      "info": {
        "expected_file_path": "E:\\CivitAI\\Users\\Spacetoonic\\LuckyPrescott _ Spirit series ( IL )\\82864573.jpeg",
        "expected_file_size": null,
        "download_url": "https://image.civitai.com/xG1nkqKTMzGDvpLrqFT7WA/e9952e3f-71a2-4d5f-883e-83cb90b99c74/original=true/e9952e3f-71a2-4d5f-883e-83cb90b99c74.jpeg",
        "page_url": "https://civitai.com/images/82864573"
      }
    },
    {
      "id": 1912369,
      "type": "lora",
      "reason": "missing",
      "info": {
        "expected_file_path": "E:\\CivitAI\\Users\\Spacetoonic\\LuckyPrescott _ Spirit series ( IL )\\LuckyPrescottIL.safetensors",
        "expected_file_size": 228459860.0,
        "presigned_url": "https://civitai-delivery-worker-prod.5ac0637cfd0766c97916cefa3764fbdf.r2.cloudflarestorage.com/modelVersion/1912369/LuckyPrescottIL.safetensors?X-Amz-Expires=86400&response-content-disposition=attachment%3B%20filename%3D%22LuckyPrescottIL.safetensors%22&X-Amz-Algorithm=AWS4-HMAC-SHA256&X-Amz-Credential=e01358d793ad6966166af8b3064953ad/20251211/us-east-1/s3/aws4_request&X-Amz-Date=20251211T040208Z&X-Amz-SignedHeaders=host&X-Amz-Signature=bd4e4822dd50d063179b0519b87c11b4ae5e5a90599dde8540b81a11f9a2180e"
      }
    },
    {
      "id": 29537394,
      "type": "image",
      "reason": "missing",
      "info": {
        "expected_file_path": "E:\\CivitAI\\Users\\Spacetoonic\\Saburi _ Secret of Cerulean sand (Pony)\\29537394.jpeg",
        "expected_file_size": null,
        "download_url": "https://image.civitai.com/xG1nkqKTMzGDvpLrqFT7WA/7e62e87d-ff26-4572-833a-9c08f450b249/original=true/7e62e87d-ff26-4572-833a-9c08f450b249.jpeg",
        "page_url": "https://civitai.com/images/29537394"
      }
    },
    {
      "id": 29537423,
      "type": "image",
      "reason": "missing",
      "info": {
        "expected_file_path": "E:\\CivitAI\\Users\\Spacetoonic\\Saburi _ Secret of Cerulean sand (Pony)\\29537423.jpeg",
        "expected_file_size": null,
        "download_url": "https://image.civitai.com/xG1nkqKTMzGDvpLrqFT7WA/441c5267-5727-401c-b06d-9ff9cc165d39/original=true/441c5267-5727-401c-b06d-9ff9cc165d39.jpeg",
        "page_url": "https://civitai.com/images/29537423"
      }
    },
    {
      "id": 25557108,
      "type": "image",
      "reason": "missing",
      "info": {
        "expected_file_path": "E:\\CivitAI\\Users\\Spacetoonic\\Will Scarlet _ Robin Hood ( 1990 anime ) [ REQUEST ]\\25557108.jpeg",
        "expected_file_size": null,
        "download_url": "https://image.civitai.com/xG1nkqKTMzGDvpLrqFT7WA/410da8bc-80df-4e8c-a088-6c81468c9a4e/original=true/410da8bc-80df-4e8c-a088-6c81468c9a4e.jpeg",
        "page_url": "https://civitai.com/images/25557108"
      }
    },
    {
      "id": 25557025,
      "type": "image",
      "reason": "missing",
      "info": {
        "expected_file_path": "E:\\CivitAI\\Users\\Spacetoonic\\Will Scarlet _ Robin Hood ( 1990 anime ) [ REQUEST ]\\25557025.jpeg",
        "expected_file_size": null,
        "download_url": "https://image.civitai.com/xG1nkqKTMzGDvpLrqFT7WA/fcc2c927-b8c4-4366-9c84-49446d5603be/original=true/fcc2c927-b8c4-4366-9c84-49446d5603be.jpeg",
        "page_url": "https://civitai.com/images/25557025"
      }
    },
    {
      "id": 753407,
      "type": "lora",
      "reason": "missing",
      "info": {
        "expected_file_path": "E:\\CivitAI\\Users\\Spacetoonic\\Will Scarlet _ Robin Hood ( 1990 anime ) [ REQUEST ]\\Will_Scarlet.safetensors",
        "expected_file_size": 228455292.0,
        "presigned_url": "https://civitai-delivery-worker-prod.5ac0637cfd0766c97916cefa3764fbdf.r2.cloudflarestorage.com/modelVersion/753407/Will_Scarlet.safetensors?X-Amz-Expires=86400&response-content-disposition=attachment%3B%20filename%3D%22Will_Scarlet.safetensors%22&X-Amz-Algorithm=AWS4-HMAC-SHA256&X-Amz-Credential=e01358d793ad6966166af8b3064953ad/20251211/us-east-1/s3/aws4_request&X-Amz-Date=20251211T040240Z&X-Amz-SignedHeaders=host&X-Amz-Signature=658127e6038c1db9a0048a6d1bf1325dd1f6e3a1d6bbbc0002361cd8b4634ec8"
      }
    },
    {
      "id": 80639578,
      "type": "image",
      "reason": "missing",
      "info": {
        "expected_file_path": "E:\\CivitAI\\Users\\Spacetoonic\\Chinmi _ Kung fu Chinmi ( Illustriuos )\\80639578.jpeg",
        "expected_file_size": null,
        "download_url": "https://image.civitai.com/xG1nkqKTMzGDvpLrqFT7WA/419d2e7d-085a-4969-bdb2-8ef8cdaf9f5c/original=true/419d2e7d-085a-4969-bdb2-8ef8cdaf9f5c.jpeg",
        "page_url": "https://civitai.com/images/80639578"
      }
    },
    {
      "id": 26229343,
      "type": "image",
      "reason": "missing",
      "info": {
        "expected_file_path": "E:\\CivitAI\\Users\\Spacetoonic\\Leo - Baskup [ REQUEST ]\\26229343.jpeg",
        "expected_file_size": null,
        "download_url": "https://image.civitai.com/xG1nkqKTMzGDvpLrqFT7WA/9aaced67-c5b3-4951-91ad-8af160ccf28e/original=true/9aaced67-c5b3-4951-91ad-8af160ccf28e.jpeg",
        "page_url": "https://civitai.com/images/26229343"
      }
    },
    {
      "id": 26229349,
      "type": "image",
      "reason": "missing",
      "info": {
        "expected_file_path": "E:\\CivitAI\\Users\\Spacetoonic\\Leo - Baskup [ REQUEST ]\\26229349.jpeg",
        "expected_file_size": null,
        "download_url": "https://image.civitai.com/xG1nkqKTMzGDvpLrqFT7WA/9d57bacf-28e1-4877-a31e-3b44330663a8/original=true/9d57bacf-28e1-4877-a31e-3b44330663a8.jpeg",
        "page_url": "https://civitai.com/images/26229349"
      }
    },
    {
      "id": 39223915,
      "type": "image",
      "reason": "missing",
      "info": {
        "expected_file_path": "E:\\CivitAI\\Users\\Spacetoonic\\Romeo & Alfredo _ Romeo's blue skies\\39223915.jpeg",
        "expected_file_size": null,
        "download_url": "https://image.civitai.com/xG1nkqKTMzGDvpLrqFT7WA/fb950c6f-7988-4fde-a534-306530943787/original=true/fb950c6f-7988-4fde-a534-306530943787.jpeg",
        "page_url": "https://civitai.com/images/39223915"
      }
    },
    {
      "id": 1298640,
      "type": "lora",
      "reason": "missing",
      "info": {
        "expected_file_path": "E:\\CivitAI\\Users\\Spacetoonic\\Chinmi _ Iron fist chinmi\\chinmi.safetensors",
        "expected_file_size": 228454980.0,
        "presigned_url": "https://civitai-delivery-worker-prod.5ac0637cfd0766c97916cefa3764fbdf.r2.cloudflarestorage.com/modelVersion/1298640/chinmi.safetensors?X-Amz-Expires=86400&response-content-disposition=attachment%3B%20filename%3D%22chinmi.safetensors%22&X-Amz-Algorithm=AWS4-HMAC-SHA256&X-Amz-Credential=e01358d793ad6966166af8b3064953ad/20251211/us-east-1/s3/aws4_request&X-Amz-Date=20251211T040338Z&X-Amz-SignedHeaders=host&X-Amz-Signature=582727ef4e092f6fd24d679e1a5096bd8b2c8cbdb3dee1b36209bdc30af5645d"
      }
    },
    {
      "id": 25417718,
      "type": "image",
      "reason": "missing",
      "info": {
        "expected_file_path": "E:\\CivitAI\\Users\\Spacetoonic\\Yamato Delgado _ Battle B-daman ( pony )\\25417718.jpeg",
        "expected_file_size": null,
        "download_url": "https://image.civitai.com/xG1nkqKTMzGDvpLrqFT7WA/ab8e7944-4f92-4429-b7a5-bf640e68f33f/original=true/ab8e7944-4f92-4429-b7a5-bf640e68f33f.jpeg",
        "page_url": "https://civitai.com/images/25417718"
      }
    },
    {
      "id": 25417644,
      "type": "image",
      "reason": "missing",
      "info": {
        "expected_file_path": "E:\\CivitAI\\Users\\Spacetoonic\\Yamato Delgado _ Battle B-daman ( pony )\\25417644.jpeg",
        "expected_file_size": null,
        "download_url": "https://image.civitai.com/xG1nkqKTMzGDvpLrqFT7WA/24d77493-73d9-48b6-b421-e0b4556f7c41/original=true/24d77493-73d9-48b6-b421-e0b4556f7c41.jpeg",
        "page_url": "https://civitai.com/images/25417644"
      }
    },
    {
      "id": 25417520,
      "type": "image",
      "reason": "missing",
      "info": {
        "expected_file_path": "E:\\CivitAI\\Users\\Spacetoonic\\Yamato Delgado _ Battle B-daman ( pony )\\25417520.jpeg",
        "expected_file_size": null,
        "download_url": "https://image.civitai.com/xG1nkqKTMzGDvpLrqFT7WA/67ce9a8c-8da4-44b8-b36d-b08aec2383c2/original=true/67ce9a8c-8da4-44b8-b36d-b08aec2383c2.jpeg",
        "page_url": "https://civitai.com/images/25417520"
      }
    },
    {
      "id": 748980,
      "type": "lora",
      "reason": "missing",
      "info": {
        "expected_file_path": "E:\\CivitAI\\Users\\Spacetoonic\\Yamato Delgado _ Battle B-daman ( pony )\\Yamato_Delgado.safetensors",
        "expected_file_size": 228455772.0,
        "presigned_url": "https://civitai-delivery-worker-prod.5ac0637cfd0766c97916cefa3764fbdf.r2.cloudflarestorage.com/modelVersion/748980/Yamato_Delgado.safetensors?X-Amz-Expires=86400&response-content-disposition=attachment%3B%20filename%3D%22Yamato_Delgado.safetensors%22&X-Amz-Algorithm=AWS4-HMAC-SHA256&X-Amz-Credential=e01358d793ad6966166af8b3064953ad/20251211/us-east-1/s3/aws4_request&X-Amz-Date=20251211T040353Z&X-Amz-SignedHeaders=host&X-Amz-Signature=47ec578c64f6627c07704455f9f44115d479c82d960b008c6f60f84c1777cab3"
      }
    },
    {
      "id": 89085951,
      "type": "image",
      "reason": "missing",
      "info": {
        "expected_file_path": "E:\\CivitAI\\Users\\Spacetoonic\\street football cartoon _ character packs ( IL )\\89085951.jpeg",
        "expected_file_size": null,
        "download_url": "https://image.civitai.com/xG1nkqKTMzGDvpLrqFT7WA/f4778d93-e903-460c-a8dc-00fb16ec4160/original=true/f4778d93-e903-460c-a8dc-00fb16ec4160.jpeg",
        "page_url": "https://civitai.com/images/89085951"
      }
    },
    {
      "id": 89085945,
      "type": "image",
      "reason": "missing",
      "info": {
        "expected_file_path": "E:\\CivitAI\\Users\\Spacetoonic\\street football cartoon _ character packs ( IL )\\89085945.jpeg",
        "expected_file_size": null,
        "download_url": "https://image.civitai.com/xG1nkqKTMzGDvpLrqFT7WA/8581ed5f-f426-4f85-a4a5-2f5151e0db76/original=true/8581ed5f-f426-4f85-a4a5-2f5151e0db76.jpeg",
        "page_url": "https://civitai.com/images/89085945"
      }
    },
    {
      "id": 89087378,
      "type": "image",
      "reason": "missing",
      "info": {
        "expected_file_path": "E:\\CivitAI\\Users\\Spacetoonic\\street football cartoon _ character packs ( IL )\\89087378.jpeg",
        "expected_file_size": null,
        "download_url": "https://image.civitai.com/xG1nkqKTMzGDvpLrqFT7WA/c602df6d-8dc7-4174-9a5b-cba726152041/original=true/c602df6d-8dc7-4174-9a5b-cba726152041.jpeg",
        "page_url": "https://civitai.com/images/89087378"
      }
    },
    {
      "id": 89087367,
      "type": "image",
      "reason": "missing",
      "info": {
        "expected_file_path": "E:\\CivitAI\\Users\\Spacetoonic\\street football cartoon _ character packs ( IL )\\89087367.jpeg",
        "expected_file_size": null,
        "download_url": "https://image.civitai.com/xG1nkqKTMzGDvpLrqFT7WA/48578b3d-f87d-4894-a92a-d4421f86d119/original=true/48578b3d-f87d-4894-a92a-d4421f86d119.jpeg",
        "page_url": "https://civitai.com/images/89087367"
      }
    },
    {
      "id": 89088239,
      "type": "image",
      "reason": "missing",
      "info": {
        "expected_file_path": "E:\\CivitAI\\Users\\Spacetoonic\\street football cartoon _ character packs ( IL )\\89088239.jpeg",
        "expected_file_size": null,
        "download_url": "https://image.civitai.com/xG1nkqKTMzGDvpLrqFT7WA/e14f3347-5fa8-4180-bd75-0e6203815400/original=true/e14f3347-5fa8-4180-bd75-0e6203815400.jpeg",
        "page_url": "https://civitai.com/images/89088239"
      }
    },
    {
      "id": 2020185,
      "type": "lora",
      "reason": "missing",
      "info": {
        "expected_file_path": "E:\\CivitAI\\Users\\Spacetoonic\\street football cartoon _ character packs ( IL )\\street_football.safetensors",
        "expected_file_size": 228460804.0,
        "presigned_url": "https://civitai-delivery-worker-prod.5ac0637cfd0766c97916cefa3764fbdf.r2.cloudflarestorage.com/modelVersion/2020185/street_football.safetensors?X-Amz-Expires=86400&response-content-disposition=attachment%3B%20filename%3D%22street_football.safetensors%22&X-Amz-Algorithm=AWS4-HMAC-SHA256&X-Amz-Credential=e01358d793ad6966166af8b3064953ad/20251211/us-east-1/s3/aws4_request&X-Amz-Date=20251211T040408Z&X-Amz-SignedHeaders=host&X-Amz-Signature=20190563822c3510d6d3e8294d026d78ff8abe6634fa822d2a4cb0e0f7a72830"
      }
    },
    {
      "id": 82188371,
      "type": "image",
      "reason": "missing",
      "info": {
        "expected_file_path": "E:\\CivitAI\\Users\\Spacetoonic\\Tsubasa Otori _ Beyblade Metal Fight ( Illustrious )\\82188371.jpeg",
        "expected_file_size": null,
        "download_url": "https://image.civitai.com/xG1nkqKTMzGDvpLrqFT7WA/02c14da9-1b63-4201-82ef-8fecdb8e64f5/original=true/02c14da9-1b63-4201-82ef-8fecdb8e64f5.jpeg",
        "page_url": "https://civitai.com/images/82188371"
      }
    },
    {
      "id": 82188891,
      "type": "image",
      "reason": "missing",
      "info": {
        "expected_file_path": "E:\\CivitAI\\Users\\Spacetoonic\\Tsubasa Otori _ Beyblade Metal Fight ( Illustrious )\\82188891.jpeg",
        "expected_file_size": null,
        "download_url": "https://image.civitai.com/xG1nkqKTMzGDvpLrqFT7WA/8cc33ab2-1d1c-4041-9310-f3279e7ff8ec/original=true/8cc33ab2-1d1c-4041-9310-f3279e7ff8ec.jpeg",
        "page_url": "https://civitai.com/images/82188891"
      }
    },
    {
      "id": 1900555,
      "type": "lora",
      "reason": "missing",
      "info": {
        "expected_file_path": "E:\\CivitAI\\Users\\Spacetoonic\\Tsubasa Otori _ Beyblade Metal Fight ( Illustrious )\\tsuabsaIL_1.safetensors",
        "expected_file_size": 114434716.0,
        "presigned_url": "https://civitai-delivery-worker-prod.5ac0637cfd0766c97916cefa3764fbdf.r2.cloudflarestorage.com/model/5072620/tsuabsail1.Xj6d.safetensors?X-Amz-Expires=86400&response-content-disposition=attachment%3B%20filename%3D%22tsuabsaIL_1.safetensors%22&X-Amz-Algorithm=AWS4-HMAC-SHA256&X-Amz-Credential=e01358d793ad6966166af8b3064953ad/20251211/us-east-1/s3/aws4_request&X-Amz-Date=20251211T040424Z&X-Amz-SignedHeaders=host&X-Amz-Signature=87d650411f16300ec4bfb4a9970b1d529b421bc18eba392086f095dbbda604e2"
      }
    },
    {
      "id": 96081262,
      "type": "image",
      "reason": "missing",
      "info": {
        "expected_file_path": "E:\\CivitAI\\Users\\Spacetoonic\\Wales _ Beyblade Metal Saga ( IL )\\96081262.jpeg",
        "expected_file_size": null,
        "download_url": "https://image.civitai.com/xG1nkqKTMzGDvpLrqFT7WA/dbfa6fcc-8306-46b0-9ed6-456299a4ccee/original=true/dbfa6fcc-8306-46b0-9ed6-456299a4ccee.jpeg",
        "page_url": "https://civitai.com/images/96081262"
      }
    },
    {
      "id": 96080666,
      "type": "image",
      "reason": "missing",
      "info": {
        "expected_file_path": "E:\\CivitAI\\Users\\Spacetoonic\\Wales _ Beyblade Metal Saga ( IL )\\96080666.jpeg",
        "expected_file_size": null,
        "download_url": "https://image.civitai.com/xG1nkqKTMzGDvpLrqFT7WA/7e8a2613-718a-4523-9717-d8be36818ffa/original=true/7e8a2613-718a-4523-9717-d8be36818ffa.jpeg",
        "page_url": "https://civitai.com/images/96080666"
      }
    },
    {
      "id": 96080665,
      "type": "image",
      "reason": "missing",
      "info": {
        "expected_file_path": "E:\\CivitAI\\Users\\Spacetoonic\\Wales _ Beyblade Metal Saga ( IL )\\96080665.jpeg",
        "expected_file_size": null,
        "download_url": "https://image.civitai.com/xG1nkqKTMzGDvpLrqFT7WA/3e3c3e8a-a0a6-437a-9bca-0c420d9216fc/original=true/3e3c3e8a-a0a6-437a-9bca-0c420d9216fc.jpeg",
        "page_url": "https://civitai.com/images/96080665"
      }
    },
    {
      "id": 96081272,
      "type": "image",
      "reason": "missing",
      "info": {
        "expected_file_path": "E:\\CivitAI\\Users\\Spacetoonic\\Wales _ Beyblade Metal Saga ( IL )\\96081272.jpeg",
        "expected_file_size": null,
        "download_url": "https://image.civitai.com/xG1nkqKTMzGDvpLrqFT7WA/aae19c9c-6bb8-497c-9da5-cc03adae06a4/original=true/aae19c9c-6bb8-497c-9da5-cc03adae06a4.jpeg",
        "page_url": "https://civitai.com/images/96081272"
      }
    },
    {
      "id": 96081723,
      "type": "image",
      "reason": "missing",
      "info": {
        "expected_file_path": "E:\\CivitAI\\Users\\Spacetoonic\\Wales _ Beyblade Metal Saga ( IL )\\96081723.jpeg",
        "expected_file_size": null,
        "download_url": "https://image.civitai.com/xG1nkqKTMzGDvpLrqFT7WA/caca7fe1-7062-42a8-8966-35083f4f2ee8/original=true/caca7fe1-7062-42a8-8966-35083f4f2ee8.jpeg",
        "page_url": "https://civitai.com/images/96081723"
      }
    },
    {
      "id": 96081826,
      "type": "image",
      "reason": "missing",
      "info": {
        "expected_file_path": "E:\\CivitAI\\Users\\Spacetoonic\\Wales _ Beyblade Metal Saga ( IL )\\96081826.jpeg",
        "expected_file_size": null,
        "download_url": "https://image.civitai.com/xG1nkqKTMzGDvpLrqFT7WA/032dcfac-219b-43ce-ab64-68d7b95d4037/original=true/032dcfac-219b-43ce-ab64-68d7b95d4037.jpeg",
        "page_url": "https://civitai.com/images/96081826"
      }
    },
    {
      "id": 2139748,
      "type": "lora",
      "reason": "missing",
      "info": {
        "expected_file_path": "E:\\CivitAI\\Users\\Spacetoonic\\Wales _ Beyblade Metal Saga ( IL )\\walesil.safetensors",
        "expected_file_size": 228456308.0,
        "presigned_url": "https://civitai-delivery-worker-prod.5ac0637cfd0766c97916cefa3764fbdf.r2.cloudflarestorage.com/modelVersion/2139748/walesil.safetensors?X-Amz-Expires=86400&response-content-disposition=attachment%3B%20filename%3D%22walesil.safetensors%22&X-Amz-Algorithm=AWS4-HMAC-SHA256&X-Amz-Credential=e01358d793ad6966166af8b3064953ad/20251211/us-east-1/s3/aws4_request&X-Amz-Date=20251211T040437Z&X-Amz-SignedHeaders=host&X-Amz-Signature=10c70dfbdb6a930a5443e02f5e48efacffc4ab7f1c2d0c3baf2c50d0353323d4"
      }
    },
    {
      "id": 50843294,
      "type": "image",
      "reason": "missing",
      "info": {
        "expected_file_path": "E:\\CivitAI\\Users\\Spacetoonic\\Murasaki _ Lupin III ( Pony )\\50843294.jpeg",
        "expected_file_size": null,
        "download_url": "https://image.civitai.com/xG1nkqKTMzGDvpLrqFT7WA/595fc11b-7e3e-499d-9702-4352f1203e4a/original=true/595fc11b-7e3e-499d-9702-4352f1203e4a.jpeg",
        "page_url": "https://civitai.com/images/50843294"
      }
    },
    {
      "id": 50843300,
      "type": "image",
      "reason": "missing",
      "info": {
        "expected_file_path": "E:\\CivitAI\\Users\\Spacetoonic\\Murasaki _ Lupin III ( Pony )\\50843300.jpeg",
        "expected_file_size": null,
        "download_url": "https://image.civitai.com/xG1nkqKTMzGDvpLrqFT7WA/65cba51a-176e-4f34-ac7b-c87ed76b4425/original=true/65cba51a-176e-4f34-ac7b-c87ed76b4425.jpeg",
        "page_url": "https://civitai.com/images/50843300"
      }
    },
    {
      "id": 1267096,
      "type": "lora",
      "reason": "missing",
      "info": {
        "expected_file_path": "E:\\CivitAI\\Users\\Spacetoonic\\Murasaki _ Lupin III ( Pony )\\Murasaki-000009.safetensors",
        "expected_file_size": 228454908.0,
        "presigned_url": "https://civitai-delivery-worker-prod.5ac0637cfd0766c97916cefa3764fbdf.r2.cloudflarestorage.com/modelVersion/1267096/Murasaki-000009.safetensors?X-Amz-Expires=86400&response-content-disposition=attachment%3B%20filename%3D%22Murasaki-000009.safetensors%22&X-Amz-Algorithm=AWS4-HMAC-SHA256&X-Amz-Credential=e01358d793ad6966166af8b3064953ad/20251211/us-east-1/s3/aws4_request&X-Amz-Date=20251211T040445Z&X-Amz-SignedHeaders=host&X-Amz-Signature=a55bc26cf42b7f9d131730e8750614980718e114a5660add1afc8fa7938133cf"
      }
    },
    {
      "id": 82069158,
      "type": "image",
      "reason": "missing",
      "info": {
        "expected_file_path": "E:\\CivitAI\\Users\\Spacetoonic\\noobai test\\82069158.jpeg",
        "expected_file_size": null,
        "download_url": "https://image.civitai.com/xG1nkqKTMzGDvpLrqFT7WA/f4d42077-edd0-4a32-b5f3-c7f43d7796eb/original=true/f4d42077-edd0-4a32-b5f3-c7f43d7796eb.jpeg",
        "page_url": "https://civitai.com/images/82069158"
      }
    },
    {
      "id": 1898475,
      "type": "lora",
      "reason": "missing",
      "info": {
        "expected_file_path": "E:\\CivitAI\\Users\\Spacetoonic\\noobai test\\tsuabsaIL.safetensors",
        "expected_file_size": 114434724.0,
        "presigned_url": "https://civitai-delivery-worker-prod.5ac0637cfd0766c97916cefa3764fbdf.r2.cloudflarestorage.com/model/5072620/tsuabsail.g1t2.safetensors?X-Amz-Expires=86400&response-content-disposition=attachment%3B%20filename%3D%22tsuabsaIL.safetensors%22&X-Amz-Algorithm=AWS4-HMAC-SHA256&X-Amz-Credential=e01358d793ad6966166af8b3064953ad/20251211/us-east-1/s3/aws4_request&X-Amz-Date=20251211T040457Z&X-Amz-SignedHeaders=host&X-Amz-Signature=9d65306085b1e29dbb29d6a04a2e816efd22f508aff0a47fc0e422e02fe756e4"
      }
    },
    {
      "id": 82072239,
      "type": "image",
      "reason": "missing",
      "info": {
        "expected_file_path": "E:\\CivitAI\\Users\\Spacetoonic\\noob ai to IL test\\82072239.jpeg",
        "expected_file_size": null,
        "download_url": "https://image.civitai.com/xG1nkqKTMzGDvpLrqFT7WA/49e01472-44d1-4695-853d-35f7ad83b05c/original=true/49e01472-44d1-4695-853d-35f7ad83b05c.jpeg",
        "page_url": "https://civitai.com/images/82072239"
      }
    },
    {
      "id": 1898537,
      "type": "lora",
      "reason": "missing",
      "info": {
        "expected_file_path": "E:\\CivitAI\\Users\\Spacetoonic\\noob ai to IL test\\tsuabsaIL.safetensors",
        "expected_file_size": 114434724.0,
        "presigned_url": "https://civitai-delivery-worker-prod.5ac0637cfd0766c97916cefa3764fbdf.r2.cloudflarestorage.com/model/5072620/tsuabsail.s2gt.safetensors?X-Amz-Expires=86400&response-content-disposition=attachment%3B%20filename%3D%22tsuabsaIL.safetensors%22&X-Amz-Algorithm=AWS4-HMAC-SHA256&X-Amz-Credential=e01358d793ad6966166af8b3064953ad/20251211/us-east-1/s3/aws4_request&X-Amz-Date=20251211T040507Z&X-Amz-SignedHeaders=host&X-Amz-Signature=b577a3f0f3348e112c78be506b12ff9b863eb81ccd2ba7e0b4971fe654579171"
      }
    },
    {
      "id": 25707320,
      "type": "image",
      "reason": "missing",
      "info": {
        "expected_file_path": "E:\\CivitAI\\Users\\Spacetoonic\\Mia Rodriguez _ BASKUP [ PONY ]\\25707320.jpeg",
        "expected_file_size": null,
        "download_url": "https://image.civitai.com/xG1nkqKTMzGDvpLrqFT7WA/e23a7821-4fd3-461b-92a2-8fe20cf29678/original=true/e23a7821-4fd3-461b-92a2-8fe20cf29678.jpeg",
        "page_url": "https://civitai.com/images/25707320"
      }
    },
    {
      "id": 25707315,
      "type": "image",
      "reason": "missing",
      "info": {
        "expected_file_path": "E:\\CivitAI\\Users\\Spacetoonic\\Mia Rodriguez _ BASKUP [ PONY ]\\25707315.jpeg",
        "expected_file_size": null,
        "download_url": "https://image.civitai.com/xG1nkqKTMzGDvpLrqFT7WA/10593d2a-c7bf-48a4-9bc7-d39cadaa2532/original=true/10593d2a-c7bf-48a4-9bc7-d39cadaa2532.jpeg",
        "page_url": "https://civitai.com/images/25707315"
      }
    },
    {
      "id": 25707323,
      "type": "image",
      "reason": "missing",
      "info": {
        "expected_file_path": "E:\\CivitAI\\Users\\Spacetoonic\\Mia Rodriguez _ BASKUP [ PONY ]\\25707323.jpeg",
        "expected_file_size": null,
        "download_url": "https://image.civitai.com/xG1nkqKTMzGDvpLrqFT7WA/c7c69072-6ce7-41db-9bc3-c106a3351ae3/original=true/c7c69072-6ce7-41db-9bc3-c106a3351ae3.jpeg",
        "page_url": "https://civitai.com/images/25707323"
      }
    },
    {
      "id": 25707325,
      "type": "image",
      "reason": "missing",
      "info": {
        "expected_file_path": "E:\\CivitAI\\Users\\Spacetoonic\\Mia Rodriguez _ BASKUP [ PONY ]\\25707325.jpeg",
        "expected_file_size": null,
        "download_url": "https://image.civitai.com/xG1nkqKTMzGDvpLrqFT7WA/6902e6d3-f4f9-40e5-997b-796245a9bd8f/original=true/6902e6d3-f4f9-40e5-997b-796245a9bd8f.jpeg",
        "page_url": "https://civitai.com/images/25707325"
      }
    },
    {
      "id": 757406,
      "type": "lora",
      "reason": "missing",
      "info": {
        "expected_file_path": "E:\\CivitAI\\Users\\Spacetoonic\\Mia Rodriguez _ BASKUP [ PONY ]\\Mia_Rodriguez.safetensors",
        "expected_file_size": 228456268.0,
        "presigned_url": "https://civitai-delivery-worker-prod.5ac0637cfd0766c97916cefa3764fbdf.r2.cloudflarestorage.com/modelVersion/757406/Mia_Rodriguez.safetensors?X-Amz-Expires=86400&response-content-disposition=attachment%3B%20filename%3D%22Mia_Rodriguez.safetensors%22&X-Amz-Algorithm=AWS4-HMAC-SHA256&X-Amz-Credential=e01358d793ad6966166af8b3064953ad/20251211/us-east-1/s3/aws4_request&X-Amz-Date=20251211T040549Z&X-Amz-SignedHeaders=host&X-Amz-Signature=7e830c5454ba909e8e96b5843ab8f6466c42dea7f40da8903eb89c72a7842d8a"
      }
    }
  ]
}